{
    "Pokémon (Gen 1–3)": [
      {"name": "Bulbasaur", "generation": 1},
      {"name": "Ivysaur", "generation": 1},
      {"name": "Venusaur", "generation": 1},
      {"name": "Charmander", "generation": 1},
      {"name": "Charmeleon", "generation": 1},
      {"name": "Charizard", "generation": 1},
      {"name": "Squirtle", "generation": 1},
      {"name": "Wartortle", "generation": 1},
      {"name": "Blastoise", "generation": 1},
      {"name": "Pidgey", "generation": 1},
      {"name": "Pidgeotto", "generation": 1},
      {"name": "Pidgeot", "generation": 1},
      {"name": "Rattata", "generation": 1},
      {"name": "Raticate", "generation": 1},
      {"name": "Spearow", "generation": 1},
      {"name": "Fearow", "generation": 1},
      {"name": "Ekans", "generation": 1},
      {"name": "Arbok", "generation": 1},
      {"name": "Pikachu", "generation": 1},
      {"name": "Raichu", "generation": 1},
      {"name": "Sandshrew", "generation": 1},
      {"name": "Sandslash", "generation": 1},
      {"name": "Nidoran♀", "generation": 1},
      {"name": "Nidorina", "generation": 1},
      {"name": "Nidoqueen", "generation": 1},
      {"name": "Nidoran♂", "generation": 1},
      {"name": "Nidorino", "generation": 1},
      {"name": "Nidoking", "generation": 1},
      {"name": "Clefairy", "generation": 1},
      {"name": "Clefable", "generation": 1},
      {"name": "Vulpix", "generation": 1},
      {"name": "Ninetales", "generation": 1},
      {"name": "Jigglypuff", "generation": 1},
      {"name": "Wigglytuff", "generation": 1},
      {"name": "Zubat", "generation": 1},
      {"name": "Golbat", "generation": 1},
      {"name": "Oddish", "generation": 1},
      {"name": "Gloom", "generation": 1},
      {"name": "Vileplume", "generation": 1},
      {"name": "Paras", "generation": 1},
      {"name": "Parasect", "generation": 1},
      {"name": "Venonat", "generation": 1},
      {"name": "Venomoth", "generation": 1},
      {"name": "Diglett", "generation": 1},
      {"name": "Dugtrio", "generation": 1},
      {"name": "Meowth", "generation": 1},
      {"name": "Persian", "generation": 1},
      {"name": "Psyduck", "generation": 1},
      {"name": "Golduck", "generation": 1},
      {"name": "Machop", "generation": 1},
      {"name": "Machoke", "generation": 1},
      {"name": "Machamp", "generation": 1},
      {"name": "Bellsprout", "generation": 1},
      {"name": "Weepinbell", "generation": 1},
      {"name": "Victreebel", "generation": 1},
      {"name": "Tentacool", "generation": 1},
      {"name": "Tentacruel", "generation": 1},
      {"name": "Geodude", "generation": 1},
      {"name": "Graveler", "generation": 1},
      {"name": "Golem", "generation": 1},
      {"name": "Ponyta", "generation": 1},
      {"name": "Rapidash", "generation": 1},
      {"name": "Slowpoke", "generation": 1},
      {"name": "Slowbro", "generation": 1},
      {"name": "Magnemite", "generation": 1},
      {"name": "Magneton", "generation": 1},
      {"name": "Farfetch'd", "generation": 1},
      {"name": "Doduo", "generation": 1},
      {"name": "Dodrio", "generation": 1},
      {"name": "Seel", "generation": 1},
      {"name": "Dewgong", "generation": 1},
      {"name": "Grimer", "generation": 1},
      {"name": "Muk", "generation": 1},
      {"name": "Shellder", "generation": 1},
      {"name": "Cloyster", "generation": 1},
      {"name": "Gastly", "generation": 1},
      {"name": "Haunter", "generation": 1},
      {"name": "Gengar", "generation": 1},
      {"name": "Onix", "generation": 1},
      {"name": "Drowzee", "generation": 1},
      {"name": "Hypno", "generation": 1},
      {"name": "Krabby", "generation": 1},
      {"name": "Kingler", "generation": 1},
      {"name": "Voltorb", "generation": 1},
      {"name": "Electrode", "generation": 1},
      {"name": "Exeggcute", "generation": 1},
      {"name": "Exeggutor", "generation": 1},
      {"name": "Cubone", "generation": 1},
      {"name": "Marowak", "generation": 1},
      {"name": "Hitmonlee", "generation": 1},
      {"name": "Hitmonchan", "generation": 1},
      {"name": "Lickitung", "generation": 1},
      {"name": "Koffing", "generation": 1},
      {"name": "Weezing", "generation": 1},
      {"name": "Rhyhorn", "generation": 1},
      {"name": "Rhydon", "generation": 1},
      {"name": "Chansey", "generation": 1},
      {"name": "Tangela", "generation": 1},
      {"name": "Kangaskhan", "generation": 1},
      {"name": "Horsea", "generation": 1},
      {"name": "Seadra", "generation": 1},
      {"name": "Goldeen", "generation": 1},
      {"name": "Seaking", "generation": 1},
      {"name": "Staryu", "generation": 1},
      {"name": "Starmie", "generation": 1},
      {"name": "Mr. Mime", "generation": 1},
      {"name": "Scyther", "generation": 1},
      {"name": "Jynx", "generation": 1},
      {"name": "Electabuzz", "generation": 1},
      {"name": "Magmar", "generation": 1},
      {"name": "Pinsir", "generation": 1},
      {"name": "Tauros", "generation": 1},
      {"name": "Magikarp", "generation": 1},
      {"name": "Gyarados", "generation": 1},
      {"name": "Lapras", "generation": 1},
      {"name": "Ditto", "generation": 1},
      {"name": "Eevee", "generation": 1},
      {"name": "Vaporeon", "generation": 1},
      {"name": "Jolteon", "generation": 1},
      {"name": "Flareon", "generation": 1},
      {"name": "Porygon", "generation": 1},
      {"name": "Omastar", "generation": 1},
      {"name": "Kabutops", "generation": 1},
      {"name": "Aerodactyl", "generation": 1},
      {"name": "Snorlax", "generation": 1},
      {"name": "Articuno", "generation": 1},
      {"name": "Zapdos", "generation": 1},
      {"name": "Moltres", "generation": 1},
      {"name": "Dratini", "generation": 1},
      {"name": "Dragonair", "generation": 1},
      {"name": "Dragonite", "generation": 1},
      {"name": "Mewtwo", "generation": 1},
      {"name": "Mew", "generation": 1},
  
      {"name": "Chikorita", "generation": 2},
      {"name": "Bayleef", "generation": 2},
      {"name": "Meganium", "generation": 2},
      {"name": "Cyndaquil", "generation": 2},
      {"name": "Quilava", "generation": 2},
      {"name": "Typhlosion", "generation": 2},
      {"name": "Totodile", "generation": 2},
      {"name": "Croconaw", "generation": 2},
      {"name": "Feraligatr", "generation": 2},
      {"name": "Sentret", "generation": 2},
      {"name": "Furret", "generation": 2},
      {"name": "Hoothoot", "generation": 2},
      {"name": "Noctowl", "generation": 2},
      {"name": "Ledyba", "generation": 2},
      {"name": "Ledian", "generation": 2},
      {"name": "Spinarak", "generation": 2},
      {"name": "Ariados", "generation": 2},
      {"name": "Crobat", "generation": 2},
      {"name": "Chinchou", "generation": 2},
      {"name": "Lanturn", "generation": 2},
      {"name": "Pichu", "generation": 2},
      {"name": "Cleffa", "generation": 2},
      {"name": "Igglybuff", "generation": 2},
      {"name": "Togepi", "generation": 2},
      {"name": "Togetic", "generation": 2},
      {"name": "Natu", "generation": 2},
      {"name": "Xatu", "generation": 2},
      {"name": "Mareep", "generation": 2},
      {"name": "Flaaffy", "generation": 2},
      {"name": "Ampharos", "generation": 2},
      {"name": "Bellossom", "generation": 2},
      {"name": "Marill", "generation": 2},
      {"name": "Azumarill", "generation": 2},
      {"name": "Sudowoodo", "generation": 2},
      {"name": "Politoed", "generation": 2},
      {"name": "Hoppip", "generation": 2},
      {"name": "Skiploom", "generation": 2},
      {"name": "Jumpluff", "generation": 2},
      {"name": "Aipom", "generation": 2},
      {"name": "Sunkern", "generation": 2},
      {"name": "Sunflora", "generation": 2},
      {"name": "Yanma", "generation": 2},
      {"name": "Wooper", "generation": 2},
      {"name": "Quagsire", "generation": 2},
      {"name": "Espeon", "generation": 2},
      {"name": "Ursaring", "generation": 2},
      {"name": "Magcargo", "generation": 2},
      {"name": "Swinub", "generation": 2},
      {"name": "Piloswine", "generation": 2},
      {"name": "Corsola", "generation": 2},
      {"name": "Remoraid", "generation": 2},
      {"name": "Octillery", "generation": 2},
      {"name": "Delibird", "generation": 2},
      {"name": "Mantine", "generation": 2},
      {"name": "Skarmory", "generation": 2},
      {"name": "Houndour", "generation": 2},
      {"name": "Houndoom", "generation": 2},
      {"name": "Phanpy", "generation": 2},
      {"name": "Donphan", "generation": 2},
      {"name": "Porygon2", "generation": 2},
      {"name": "Stantler", "generation": 2},
      {"name": "Smeargle", "generation": 2},
      {"name": "Tyrogue", "generation": 2},
      {"name": "Hitmontop", "generation": 2},
      {"name": "Smoochum", "generation": 2},
      {"name": "Elekid", "generation": 2},
      {"name": "Magby", "generation": 2},
      {"name": "Miltank", "generation": 2},
      {"name": "Blissey", "generation": 2},
      {"name": "Raikou", "generation": 2},
      {"name": "Entei", "generation": 2},
      {"name": "Suicune", "generation": 2},
      {"name": "Larvitar", "generation": 2},
      {"name": "Pupitar", "generation": 2},
      {"name": "Tyranitar", "generation": 2},
      {"name": "Lugia", "generation": 2},
      {"name": "Ho-Oh", "generation": 2},
      {"name": "Celebi", "generation": 2},
  
      {"name": "Treecko", "generation": 3},
      {"name": "Grovyle", "generation": 3},
      {"name": "Sceptile", "generation": 3},
      {"name": "Torchic", "generation": 3},
      {"name": "Combusken", "generation": 3},
      {"name": "Blaziken", "generation": 3},
      {"name": "Mudkip", "generation": 3},
      {"name": "Marshtomp", "generation": 3},
      {"name": "Swampert", "generation": 3},
      {"name": "Poochyena", "generation": 3},
      {"name": "Mightyena", "generation": 3},
      {"name": "Zigzagoon", "generation": 3},
      {"name": "Linoone", "generation": 3},
      {"name": "Wurmple", "generation": 3},
      {"name": "Silcoon", "generation": 3},
      {"name": "Beautifly", "generation": 3},
      {"name": "Cascoon", "generation": 3},
      {"name": "Dustox", "generation": 3},
      {"name": "Lotad", "generation": 3},
      {"name": "Lombre", "generation": 3},
      {"name": "Ludicolo", "generation": 3},
      {"name": "Seedot", "generation": 3},
      {"name": "Nuzleaf", "generation": 3},
      {"name": "Shiftry", "generation": 3},
      {"name": "Taillow", "generation": 3},
      {"name": "Swellow", "generation": 3},
      {"name": "Wingull", "generation": 3},
      {"name": "Pelipper", "generation": 3},
      {"name": "Ralts", "generation": 3},
      {"name": "Kirlia", "generation": 3},
      {"name": "Gardevoir", "generation": 3},
      {"name": "Surskit", "generation": 3},
      {"name": "Masquerain", "generation": 3},
      {"name": "Shroomish", "generation": 3},
      {"name": "Breloom", "generation": 3},
      {"name": "Slakoth", "generation": 3},
      {"name": "Vigoroth", "generation": 3},
      {"name": "Slaking", "generation": 3},
      {"name": "Nincada", "generation": 3},
      {"name": "Ninjask", "generation": 3},
      {"name": "Shedinja", "generation": 3},
      {"name": "Whismur", "generation": 3},
      {"name": "Loudred", "generation": 3},
      {"name": "Exploud", "generation": 3},
      {"name": "Makuhita", "generation": 3},
      {"name": "Hariyama", "generation": 3},
      {"name": "Azurill", "generation": 3},
      {"name": "Nosepass", "generation": 3},
      {"name": "Skitty", "generation": 3},
      {"name": "Delcatty", "generation": 3},
      {"name": "Sableye", "generation": 3},
      {"name": "Mawile", "generation": 3},
      {"name": "Aron", "generation": 3},
      {"name": "Lairon", "generation": 3},
      {"name": "Aggron", "generation": 3},
      {"name": "Meditite", "generation": 3},
      {"name": "Medicham", "generation": 3},
      {"name": "Electrike", "generation": 3},
      {"name": "Manectric", "generation": 3},
      {"name": "Plusle", "generation": 3},
      {"name": "Minun", "generation": 3},
      {"name": "Volbeat", "generation": 3},
      {"name": "Illumise", "generation": 3},
      {"name": "Roselia", "generation": 3},
      {"name": "Gulpin", "generation": 3},
      {"name": "Swalot", "generation": 3},
      {"name": "Carvanha", "generation": 3},
      {"name": "Sharpedo", "generation": 3},
      {"name": "Wailmer", "generation": 3},
      {"name": "Wailord", "generation": 3},
      {"name": "Numel", "generation": 3},
      {"name": "Camerupt", "generation": 3},
      {"name": "Torkoal", "generation": 3},
      {"name": "Spoink", "generation": 3},
      {"name": "Grumpig", "generation": 3},
      {"name": "Spinda", "generation": 3},
      {"name": "Trapinch", "generation": 3},
      {"name": "Vibrava", "generation": 3},
      {"name": "Flygon", "generation": 3},
      {"name": "Cacnea", "generation": 3},
      {"name": "Cacturne", "generation": 3},
      {"name": "Swablu", "generation": 3},
      {"name": "Altaria", "generation": 3},
      {"name": "Zangoose", "generation": 3},
      {"name": "Seviper", "generation": 3},
      {"name": "Lunatone", "generation": 3},
      {"name": "Solrock", "generation": 3},
      {"name": "Barboach", "generation": 3},
      {"name": "Whiscash", "generation": 3},
      {"name": "Corphish", "generation": 3},
      {"name": "Crawdaunt", "generation": 3},
      {"name": "Baltoy", "generation": 3},
      {"name": "Claydol", "generation": 3},
      {"name": "Lileep", "generation": 3},
      {"name": "Cradily", "generation": 3},
      {"name": "Anorith", "generation": 3},
      {"name": "Armaldo", "generation": 3},
      {"name": "Feebas", "generation": 3},
      {"name": "Milotic", "generation": 3},
      {"name": "Castform", "generation": 3},
      {"name": "Kecleon", "generation": 3},
      {"name": "Shuppet", "generation": 3},
      {"name": "Banette", "generation": 3},
      {"name": "Duskull", "generation": 3},
      {"name": "Dusclops", "generation": 3},
      {"name": "Tropius", "generation": 3},
      {"name": "Chimecho", "generation": 3},
      {"name": "Absol", "generation": 3},
      {"name": "Snorunt", "generation": 3},
      {"name": "Glalie", "generation": 3},
      {"name": "Spheal", "generation": 3},
      {"name": "Sealeo", "generation": 3},
      {"name": "Walrein", "generation": 3},
      {"name": "Clamperl", "generation": 3},
      {"name": "Huntail", "generation": 3},
      {"name": "Gorebyss", "generation": 3},
      {"name": "Relicanth", "generation": 3},
      {"name": "Luvdisc", "generation": 3},
      {"name": "Beldum", "generation": 3},
      {"name": "Metang", "generation": 3},
      {"name": "Metagross", "generation": 3},
      {"name": "Regirock", "generation": 3},
      {"name": "Regice", "generation": 3},
      {"name": "Registeel", "generation": 3},
      {"name": "Latias", "generation": 3},
      {"name": "Latios", "generation": 3},
      {"name": "Kyogre", "generation": 3},
      {"name": "Groudon", "generation": 3},
      {"name": "Rayquaza", "generation": 3},
      {"name": "Jirachi", "generation": 3},
      {"name": "Deoxys", "generation": 3}
    ]
}